CHANGELOG.md
LICENSE
MANIFEST.in
README.md
setup.cfg
setup.py
examples/direct_session.py
examples/http_example_explanatory.py
examples/http_example_quickstart.py
examples/http_example_rsa_authentication.py
examples/websocket_example_explanatory.py
examples/websocket_example_quickstart.py
examples/websocket_example_rsa_authentication.py
examples/websocket_trading_example_quickstart.py
examples/wrapper_class.py
pybit/__init__.py
pybit/_helpers.py
pybit/_http_manager.py
pybit/_v5_account.py
pybit/_v5_asset.py
pybit/_v5_broker.py
pybit/_v5_crypto_loan.py
pybit/_v5_earn.py
pybit/_v5_institutional_loan.py
pybit/_v5_market.py
pybit/_v5_misc.py
pybit/_v5_position.py
pybit/_v5_pre_upgrade.py
pybit/_v5_spot_leverage_token.py
pybit/_v5_spot_margin_trade.py
pybit/_v5_trade.py
pybit/_v5_user.py
pybit/_websocket_stream.py
pybit/_websocket_trading.py
pybit/account.py
pybit/asset.py
pybit/broker.py
pybit/crypto_loan.py
pybit/earn.py
pybit/exceptions.py
pybit/helpers.py
pybit/institutional_loan.py
pybit/market.py
pybit/misc.py
pybit/position.py
pybit/pre_upgrade.py
pybit/spot_leverage_token.py
pybit/spot_margin_trade.py
pybit/trade.py
pybit/unified_trading.py
pybit/user.py
pybit.egg-info/PKG-INFO
pybit.egg-info/SOURCES.txt
pybit.egg-info/dependency_links.txt
pybit.egg-info/not-zip-safe
pybit.egg-info/requires.txt
pybit.egg-info/top_level.txt