Metadata-Version: 2.1
Name: pybit
Version: 5.10.0
Summary: Python3 Bybit HTTP/WebSocket API Connector
Home-page: https://github.com/bybit-exchange/pybit
Author: Dexter Dickinson
Author-email: dexter.dickinson@bybit.com
License: MIT License
Keywords: bybit api connector
Platform: UNKNOWN
Classifier: Development Status :: 4 - Beta
Classifier: Intended Audience :: Developers
Classifier: Topic :: Software Development :: Libraries :: Python Modules
Classifier: License :: OSI Approved :: MIT License
Classifier: Programming Language :: Python :: 3.9
Classifier: Programming Language :: Python :: 3.10
Requires-Python: >=3.6
